{
  "level": "A2",
  "language": "fr",
  "total_lessons": 15,
  "exercises_per_lesson": 10,
  "cefr_standard": "A2 - Élémentaire",
  "lessons": [
    {
      "lesson_number": 1,
      "title": "Messages courts",
      "slug": "a2-lecon-1-messages-courts",
      "objective": "Comprendre des textes de compréhension écrite niveau A2",
      "vocabulary_focus": [
        "email",
        "rdv",
        "confirmation"
      ],
      "exercises": [
        {
          "exercise_number": 1,
          "type": "multiple_choice",
          "passage_title": "Passage lecteur",
          "passage_text": "Vente samedi matin. Vêtements enfants.",
          "question": "Question 1 sur le passage?",
          "options": {
            "A": "Option A pour question 1",
            "B": "Option B pour question 1",
            "C": "Option C pour question 1",
            "D": "Option D pour question 1"
          },
          "correct_answer": "B",
          "explanation": "Explication pour l'exercice 1.",
          "difficulty_progression": 2
        },
        {
          "exercise_number": 2,
          "type": "vrai_faux",
          "passage_title": "Passage lecteur",
          "passage_text": "Rappel: vaccination jeudi 10h.",
          "question": "Question 2 sur le passage?",
          "options": {},
          "correct_answer": "Vrai",
          "explanation": "Explication pour l'exercice 2.",
          "difficulty_progression": 3
        },
        {
          "exercise_number": 3,
          "type": "multiple_choice",
          "passage_title": "Passage lecteur",
          "passage_text": "Appartement à louer. Proche métro.",
          "question": "Question 3 sur le passage?",
          "options": {
            "A": "Option A pour question 3",
            "B": "Option B pour question 3",
            "C": "Option C pour question 3",
            "D": "Option D pour question 3"
          },
          "correct_answer": "D",
          "explanation": "Explication pour l'exercice 3.",
          "difficulty_progression": 1
        },
        {
          "exercise_number": 4,
          "type": "vrai_faux",
          "passage_title": "Passage lecteur",
          "passage_text": "Cours yoga mardi 18h.",
          "question": "Question 4 sur le passage?",
          "options": {},
          "correct_answer": "Vrai",
          "explanation": "Explication pour l'exercice 4.",
          "difficulty_progression": 2
        },
        {
          "exercise_number": 5,
          "type": "multiple_choice",
          "passage_title": "Passage lecteur",
          "passage_text": "Je confirme notre rendez-vous demain à 15h.",
          "question": "Question 5 sur le passage?",
          "options": {
            "A": "Option A pour question 5",
            "B": "Option B pour question 5",
            "C": "Option C pour question 5",
            "D": "Option D pour question 5"
          },
          "correct_answer": "B",
          "explanation": "Explication pour l'exercice 5.",
          "difficulty_progression": 3
        },
        {
          "exercise_number": 6,
          "type": "vrai_faux",
          "passage_title": "Passage lecteur",
          "passage_text": "Vente samedi matin. Vêtements enfants.",
          "question": "Question 6 sur le passage?",
          "options": {},
          "correct_answer": "Vrai",
          "explanation": "Explication pour l'exercice 6.",
          "difficulty_progression": 1
        },
        {
          "exercise_number": 7,
          "type": "multiple_choice",
          "passage_title": "Passage lecteur",
          "passage_text": "Rappel: vaccination jeudi 10h.",
          "question": "Question 7 sur le passage?",
          "options": {
            "A": "Option A pour question 7",
            "B": "Option B pour question 7",
            "C": "Option C pour question 7",
            "D": "Option D pour question 7"
          },
          "correct_answer": "D",
          "explanation": "Explication pour l'exercice 7.",
          "difficulty_progression": 2
        },
        {
          "exercise_number": 8,
          "type": "vrai_faux",
          "passage_title": "Passage lecteur",
          "passage_text": "Appartement à louer. Proche métro.",
          "question": "Question 8 sur le passage?",
          "options": {},
          "correct_answer": "Vrai",
          "explanation": "Explication pour l'exercice 8.",
          "difficulty_progression": 3
        },
        {
          "exercise_number": 9,
          "type": "multiple_choice",
          "passage_title": "Passage lecteur",
          "passage_text": "Cours yoga mardi 18h.",
          "question": "Question 9 sur le passage?",
          "options": {
            "A": "Option A pour question 9",
            "B": "Option B pour question 9",
            "C": "Option C pour question 9",
            "D": "Option D pour question 9"
          },
          "correct_answer": "B",
          "explanation": "Explication pour l'exercice 9.",
          "difficulty_progression": 1
        },
        {
          "exercise_number": 10,
          "type": "vrai_faux",
          "passage_title": "Passage lecteur",
          "passage_text": "Je confirme notre rendez-vous demain à 15h.",
          "question": "Question 10 sur le passage?",
          "options": {},
          "correct_answer": "Vrai",
          "explanation": "Explication pour l'exercice 10.",
          "difficulty_progression": 2
        }
      ]
    },
    {
      "lesson_number": 2,
      "title": "Directions",
      "slug": "a2-lecon-2-directions",
      "objective": "Comprendre des textes de compréhension écrite niveau A2",
      "vocabulary_focus": [
        "gauche",
        "droite",
        "métro",
        "route"
      ],
      "exercises": [
        {
          "exercise_number": 1,
          "type": "multiple_choice",
          "passage_title": "Passage lecteur",
          "passage_text": "Prenez la ligne rouge.",
          "question": "Question 1 sur le passage?",
          "options": {
            "A": "Option A pour question 1",
            "B": "Option B pour question 1",
            "C": "Option C pour question 1",
            "D": "Option D pour question 1"
          },
          "correct_answer": "B",
          "explanation": "Explication pour l'exercice 1.",
          "difficulty_progression": 2
        },
        {
          "exercise_number": 2,
          "type": "vrai_faux",
          "passage_title": "Passage lecteur",
          "passage_text": "Station fermée dimanche.",
          "question": "Question 2 sur le passage?",
          "options": {},
          "correct_answer": "Vrai",
          "explanation": "Explication pour l'exercice 2.",
          "difficulty_progression": 3
        },
        {
          "exercise_number": 3,
          "type": "multiple_choice",
          "passage_title": "Passage lecteur",
          "passage_text": "Parking central.",
          "question": "Question 3 sur le passage?",
          "options": {
            "A": "Option A pour question 3",
            "B": "Option B pour question 3",
            "C": "Option C pour question 3",
            "D": "Option D pour question 3"
          },
          "correct_answer": "D",
          "explanation": "Explication pour l'exercice 3.",
          "difficulty_progression": 1
        },
        {
          "exercise_number": 4,
          "type": "vrai_faux",
          "passage_title": "Passage lecteur",
          "passage_text": "Route nationale 1.",
          "question": "Question 4 sur le passage?",
          "options": {},
          "correct_answer": "Vrai",
          "explanation": "Explication pour l'exercice 4.",
          "difficulty_progression": 2
        },
        {
          "exercise_number": 5,
          "type": "multiple_choice",
          "passage_title": "Passage lecteur",
          "passage_text": "Tournez à gauche puis droit.",
          "question": "Question 5 sur le passage?",
          "options": {
            "A": "Option A pour question 5",
            "B": "Option B pour question 5",
            "C": "Option C pour question 5",
            "D": "Option D pour question 5"
          },
          "correct_answer": "B",
          "explanation": "Explication pour l'exercice 5.",
          "difficulty_progression": 3
        },
        {
          "exercise_number": 6,
          "type": "vrai_faux",
          "passage_title": "Passage lecteur",
          "passage_text": "Prenez la ligne rouge.",
          "question": "Question 6 sur le passage?",
          "options": {},
          "correct_answer": "Vrai",
          "explanation": "Explication pour l'exercice 6.",
          "difficulty_progression": 1
        },
        {
          "exercise_number": 7,
          "type": "multiple_choice",
          "passage_title": "Passage lecteur",
          "passage_text": "Station fermée dimanche.",
          "question": "Question 7 sur le passage?",
          "options": {
            "A": "Option A pour question 7",
            "B": "Option B pour question 7",
            "C": "Option C pour question 7",
            "D": "Option D pour question 7"
          },
          "correct_answer": "D",
          "explanation": "Explication pour l'exercice 7.",
          "difficulty_progression": 2
        },
        {
          "exercise_number": 8,
          "type": "vrai_faux",
          "passage_title": "Passage lecteur",
          "passage_text": "Parking central.",
          "question": "Question 8 sur le passage?",
          "options": {},
          "correct_answer": "Vrai",
          "explanation": "Explication pour l'exercice 8.",
          "difficulty_progression": 3
        },
        {
          "exercise_number": 9,
          "type": "multiple_choice",
          "passage_title": "Passage lecteur",
          "passage_text": "Route nationale 1.",
          "question": "Question 9 sur le passage?",
          "options": {
            "A": "Option A pour question 9",
            "B": "Option B pour question 9",
            "C": "Option C pour question 9",
            "D": "Option D pour question 9"
          },
          "correct_answer": "B",
          "explanation": "Explication pour l'exercice 9.",
          "difficulty_progression": 1
        },
        {
          "exercise_number": 10,
          "type": "vrai_faux",
          "passage_title": "Passage lecteur",
          "passage_text": "Tournez à gauche puis droit.",
          "question": "Question 10 sur le passage?",
          "options": {},
          "correct_answer": "Vrai",
          "explanation": "Explication pour l'exercice 10.",
          "difficulty_progression": 2
        }
      ]
    },
    {
      "lesson_number": 3,
      "title": "Horaires détaillés",
      "slug": "a2-lecon-3-horaires-détaillés",
      "objective": "Comprendre des textes de compréhension écrite niveau A2",
      "vocabulary_focus": [
        "ouverture",
        "fermeture",
        "horaire"
      ],
      "exercises": [
        {
          "exercise_number": 1,
          "type": "multiple_choice",
          "passage_title": "Passage lecteur",
          "passage_text": "Bibliothèque: lundi-samedi 9h-19h.",
          "question": "Question 1 sur le passage?",
          "options": {
            "A": "Option A pour question 1",
            "B": "Option B pour question 1",
            "C": "Option C pour question 1",
            "D": "Option D pour question 1"
          },
          "correct_answer": "B",
          "explanation": "Explication pour l'exercice 1.",
          "difficulty_progression": 2
        },
        {
          "exercise_number": 2,
          "type": "vrai_faux",
          "passage_title": "Passage lecteur",
          "passage_text": "Magasin fermé dimanche.",
          "question": "Question 2 sur le passage?",
          "options": {},
          "correct_answer": "Vrai",
          "explanation": "Explication pour l'exercice 2.",
          "difficulty_progression": 3
        },
        {
          "exercise_number": 3,
          "type": "multiple_choice",
          "passage_title": "Passage lecteur",
          "passage_text": "Déjeuner 12h-14h.",
          "question": "Question 3 sur le passage?",
          "options": {
            "A": "Option A pour question 3",
            "B": "Option B pour question 3",
            "C": "Option C pour question 3",
            "D": "Option D pour question 3"
          },
          "correct_answer": "D",
          "explanation": "Explication pour l'exercice 3.",
          "difficulty_progression": 1
        },
        {
          "exercise_number": 4,
          "type": "vrai_faux",
          "passage_title": "Passage lecteur",
          "passage_text": "Service 24h/24.",
          "question": "Question 4 sur le passage?",
          "options": {},
          "correct_answer": "Vrai",
          "explanation": "Explication pour l'exercice 4.",
          "difficulty_progression": 2
        },
        {
          "exercise_number": 5,
          "type": "multiple_choice",
          "passage_title": "Passage lecteur",
          "passage_text": "Métro: 5h30-0h30.",
          "question": "Question 5 sur le passage?",
          "options": {
            "A": "Option A pour question 5",
            "B": "Option B pour question 5",
            "C": "Option C pour question 5",
            "D": "Option D pour question 5"
          },
          "correct_answer": "B",
          "explanation": "Explication pour l'exercice 5.",
          "difficulty_progression": 3
        },
        {
          "exercise_number": 6,
          "type": "vrai_faux",
          "passage_title": "Passage lecteur",
          "passage_text": "Bibliothèque: lundi-samedi 9h-19h.",
          "question": "Question 6 sur le passage?",
          "options": {},
          "correct_answer": "Vrai",
          "explanation": "Explication pour l'exercice 6.",
          "difficulty_progression": 1
        },
        {
          "exercise_number": 7,
          "type": "multiple_choice",
          "passage_title": "Passage lecteur",
          "passage_text": "Magasin fermé dimanche.",
          "question": "Question 7 sur le passage?",
          "options": {
            "A": "Option A pour question 7",
            "B": "Option B pour question 7",
            "C": "Option C pour question 7",
            "D": "Option D pour question 7"
          },
          "correct_answer": "D",
          "explanation": "Explication pour l'exercice 7.",
          "difficulty_progression": 2
        },
        {
          "exercise_number": 8,
          "type": "vrai_faux",
          "passage_title": "Passage lecteur",
          "passage_text": "Déjeuner 12h-14h.",
          "question": "Question 8 sur le passage?",
          "options": {},
          "correct_answer": "Vrai",
          "explanation": "Explication pour l'exercice 8.",
          "difficulty_progression": 3
        },
        {
          "exercise_number": 9,
          "type": "multiple_choice",
          "passage_title": "Passage lecteur",
          "passage_text": "Service 24h/24.",
          "question": "Question 9 sur le passage?",
          "options": {
            "A": "Option A pour question 9",
            "B": "Option B pour question 9",
            "C": "Option C pour question 9",
            "D": "Option D pour question 9"
          },
          "correct_answer": "B",
          "explanation": "Explication pour l'exercice 9.",
          "difficulty_progression": 1
        },
        {
          "exercise_number": 10,
          "type": "vrai_faux",
          "passage_title": "Passage lecteur",
          "passage_text": "Métro: 5h30-0h30.",
          "question": "Question 10 sur le passage?",
          "options": {},
          "correct_answer": "Vrai",
          "explanation": "Explication pour l'exercice 10.",
          "difficulty_progression": 2
        }
      ]
    },
    {
      "lesson_number": 4,
      "title": "Annonces immobilières",
      "slug": "a2-lecon-4-annonces-immobilières",
      "objective": "Comprendre des textes de compréhension écrite niveau A2",
      "vocabulary_focus": [
        "louer",
        "studio",
        "cuisine"
      ],
      "exercises": [
        {
          "exercise_number": 1,
          "type": "multiple_choice",
          "passage_title": "Passage lecteur",
          "passage_text": "2 pièces, cuisine ouverte.",
          "question": "Question 1 sur le passage?",
          "options": {
            "A": "Option A pour question 1",
            "B": "Option B pour question 1",
            "C": "Option C pour question 1",
            "D": "Option D pour question 1"
          },
          "correct_answer": "B",
          "explanation": "Explication pour l'exercice 1.",
          "difficulty_progression": 2
        },
        {
          "exercise_number": 2,
          "type": "vrai_faux",
          "passage_title": "Passage lecteur",
          "passage_text": "Balcon, parking.",
          "question": "Question 2 sur le passage?",
          "options": {},
          "correct_answer": "Vrai",
          "explanation": "Explication pour l'exercice 2.",
          "difficulty_progression": 3
        },
        {
          "exercise_number": 3,
          "type": "multiple_choice",
          "passage_title": "Passage lecteur",
          "passage_text": "Visite samedi.",
          "question": "Question 3 sur le passage?",
          "options": {
            "A": "Option A pour question 3",
            "B": "Option B pour question 3",
            "C": "Option C pour question 3",
            "D": "Option D pour question 3"
          },
          "correct_answer": "D",
          "explanation": "Explication pour l'exercice 3.",
          "difficulty_progression": 1
        },
        {
          "exercise_number": 4,
          "type": "vrai_faux",
          "passage_title": "Passage lecteur",
          "passage_text": "Proche écoles.",
          "question": "Question 4 sur le passage?",
          "options": {},
          "correct_answer": "Vrai",
          "explanation": "Explication pour l'exercice 4.",
          "difficulty_progression": 2
        },
        {
          "exercise_number": 5,
          "type": "multiple_choice",
          "passage_title": "Passage lecteur",
          "passage_text": "Studio 30m² à louer 600€.",
          "question": "Question 5 sur le passage?",
          "options": {
            "A": "Option A pour question 5",
            "B": "Option B pour question 5",
            "C": "Option C pour question 5",
            "D": "Option D pour question 5"
          },
          "correct_answer": "B",
          "explanation": "Explication pour l'exercice 5.",
          "difficulty_progression": 3
        },
        {
          "exercise_number": 6,
          "type": "vrai_faux",
          "passage_title": "Passage lecteur",
          "passage_text": "2 pièces, cuisine ouverte.",
          "question": "Question 6 sur le passage?",
          "options": {},
          "correct_answer": "Vrai",
          "explanation": "Explication pour l'exercice 6.",
          "difficulty_progression": 1
        },
        {
          "exercise_number": 7,
          "type": "multiple_choice",
          "passage_title": "Passage lecteur",
          "passage_text": "Balcon, parking.",
          "question": "Question 7 sur le passage?",
          "options": {
            "A": "Option A pour question 7",
            "B": "Option B pour question 7",
            "C": "Option C pour question 7",
            "D": "Option D pour question 7"
          },
          "correct_answer": "D",
          "explanation": "Explication pour l'exercice 7.",
          "difficulty_progression": 2
        },
        {
          "exercise_number": 8,
          "type": "vrai_faux",
          "passage_title": "Passage lecteur",
          "passage_text": "Visite samedi.",
          "question": "Question 8 sur le passage?",
          "options": {},
          "correct_answer": "Vrai",
          "explanation": "Explication pour l'exercice 8.",
          "difficulty_progression": 3
        },
        {
          "exercise_number": 9,
          "type": "multiple_choice",
          "passage_title": "Passage lecteur",
          "passage_text": "Proche écoles.",
          "question": "Question 9 sur le passage?",
          "options": {
            "A": "Option A pour question 9",
            "B": "Option B pour question 9",
            "C": "Option C pour question 9",
            "D": "Option D pour question 9"
          },
          "correct_answer": "B",
          "explanation": "Explication pour l'exercice 9.",
          "difficulty_progression": 1
        },
        {
          "exercise_number": 10,
          "type": "vrai_faux",
          "passage_title": "Passage lecteur",
          "passage_text": "Studio 30m² à louer 600€.",
          "question": "Question 10 sur le passage?",
          "options": {},
          "correct_answer": "Vrai",
          "explanation": "Explication pour l'exercice 10.",
          "difficulty_progression": 2
        }
      ]
    },
    {
      "lesson_number": 5,
      "title": "Invitations et événements",
      "slug": "a2-lecon-5-invitations-et-événements",
      "objective": "Comprendre des textes de compréhension écrite niveau A2",
      "vocabulary_focus": [
        "fête",
        "concert",
        "dîner"
      ],
      "exercises": [
        {
          "exercise_number": 1,
          "type": "multiple_choice",
          "passage_title": "Passage lecteur",
          "passage_text": "Entrée: 20 euros.",
          "question": "Question 1 sur le passage?",
          "options": {
            "A": "Option A pour question 1",
            "B": "Option B pour question 1",
            "C": "Option C pour question 1",
            "D": "Option D pour question 1"
          },
          "correct_answer": "B",
          "explanation": "Explication pour l'exercice 1.",
          "difficulty_progression": 2
        },
        {
          "exercise_number": 2,
          "type": "vrai_faux",
          "passage_title": "Passage lecteur",
          "passage_text": "Dîner famille samedi.",
          "question": "Question 2 sur le passage?",
          "options": {},
          "correct_answer": "Vrai",
          "explanation": "Explication pour l'exercice 2.",
          "difficulty_progression": 3
        },
        {
          "exercise_number": 3,
          "type": "multiple_choice",
          "passage_title": "Passage lecteur",
          "passage_text": "Match football.",
          "question": "Question 3 sur le passage?",
          "options": {
            "A": "Option A pour question 3",
            "B": "Option B pour question 3",
            "C": "Option C pour question 3",
            "D": "Option D pour question 3"
          },
          "correct_answer": "D",
          "explanation": "Explication pour l'exercice 3.",
          "difficulty_progression": 1
        },
        {
          "exercise_number": 4,
          "type": "vrai_faux",
          "passage_title": "Passage lecteur",
          "passage_text": "Place assise.",
          "question": "Question 4 sur le passage?",
          "options": {},
          "correct_answer": "Vrai",
          "explanation": "Explication pour l'exercice 4.",
          "difficulty_progression": 2
        },
        {
          "exercise_number": 5,
          "type": "multiple_choice",
          "passage_title": "Passage lecteur",
          "passage_text": "Invitation: concert dimanche 20h.",
          "question": "Question 5 sur le passage?",
          "options": {
            "A": "Option A pour question 5",
            "B": "Option B pour question 5",
            "C": "Option C pour question 5",
            "D": "Option D pour question 5"
          },
          "correct_answer": "B",
          "explanation": "Explication pour l'exercice 5.",
          "difficulty_progression": 3
        },
        {
          "exercise_number": 6,
          "type": "vrai_faux",
          "passage_title": "Passage lecteur",
          "passage_text": "Entrée: 20 euros.",
          "question": "Question 6 sur le passage?",
          "options": {},
          "correct_answer": "Vrai",
          "explanation": "Explication pour l'exercice 6.",
          "difficulty_progression": 1
        },
        {
          "exercise_number": 7,
          "type": "multiple_choice",
          "passage_title": "Passage lecteur",
          "passage_text": "Dîner famille samedi.",
          "question": "Question 7 sur le passage?",
          "options": {
            "A": "Option A pour question 7",
            "B": "Option B pour question 7",
            "C": "Option C pour question 7",
            "D": "Option D pour question 7"
          },
          "correct_answer": "D",
          "explanation": "Explication pour l'exercice 7.",
          "difficulty_progression": 2
        },
        {
          "exercise_number": 8,
          "type": "vrai_faux",
          "passage_title": "Passage lecteur",
          "passage_text": "Match football.",
          "question": "Question 8 sur le passage?",
          "options": {},
          "correct_answer": "Vrai",
          "explanation": "Explication pour l'exercice 8.",
          "difficulty_progression": 3
        },
        {
          "exercise_number": 9,
          "type": "multiple_choice",
          "passage_title": "Passage lecteur",
          "passage_text": "Place assise.",
          "question": "Question 9 sur le passage?",
          "options": {
            "A": "Option A pour question 9",
            "B": "Option B pour question 9",
            "C": "Option C pour question 9",
            "D": "Option D pour question 9"
          },
          "correct_answer": "B",
          "explanation": "Explication pour l'exercice 9.",
          "difficulty_progression": 1
        },
        {
          "exercise_number": 10,
          "type": "vrai_faux",
          "passage_title": "Passage lecteur",
          "passage_text": "Invitation: concert dimanche 20h.",
          "question": "Question 10 sur le passage?",
          "options": {},
          "correct_answer": "Vrai",
          "explanation": "Explication pour l'exercice 10.",
          "difficulty_progression": 2
        }
      ]
    },
    {
      "lesson_number": 6,
      "title": "Conseils et notes",
      "slug": "a2-lecon-6-conseils-et-notes",
      "objective": "Comprendre des textes de compréhension écrite niveau A2",
      "vocabulary_focus": [
        "conseil",
        "attention",
        "important"
      ],
      "exercises": [
        {
          "exercise_number": 1,
          "type": "multiple_choice",
          "passage_title": "Passage lecteur",
          "passage_text": "Attention: travaux.",
          "question": "Question 1 sur le passage?",
          "options": {
            "A": "Option A pour question 1",
            "B": "Option B pour question 1",
            "C": "Option C pour question 1",
            "D": "Option D pour question 1"
          },
          "correct_answer": "B",
          "explanation": "Explication pour l'exercice 1.",
          "difficulty_progression": 2
        },
        {
          "exercise_number": 2,
          "type": "vrai_faux",
          "passage_title": "Passage lecteur",
          "passage_text": "Important: retards possibles.",
          "question": "Question 2 sur le passage?",
          "options": {},
          "correct_answer": "Vrai",
          "explanation": "Explication pour l'exercice 2.",
          "difficulty_progression": 3
        },
        {
          "exercise_number": 3,
          "type": "multiple_choice",
          "passage_title": "Passage lecteur",
          "passage_text": "À bientôt.",
          "question": "Question 3 sur le passage?",
          "options": {
            "A": "Option A pour question 3",
            "B": "Option B pour question 3",
            "C": "Option C pour question 3",
            "D": "Option D pour question 3"
          },
          "correct_answer": "D",
          "explanation": "Explication pour l'exercice 3.",
          "difficulty_progression": 1
        },
        {
          "exercise_number": 4,
          "type": "vrai_faux",
          "passage_title": "Passage lecteur",
          "passage_text": "Rappel: vaccination.",
          "question": "Question 4 sur le passage?",
          "options": {},
          "correct_answer": "Vrai",
          "explanation": "Explication pour l'exercice 4.",
          "difficulty_progression": 2
        },
        {
          "exercise_number": 5,
          "type": "multiple_choice",
          "passage_title": "Passage lecteur",
          "passage_text": "Évitez aliments allergènes.",
          "question": "Question 5 sur le passage?",
          "options": {
            "A": "Option A pour question 5",
            "B": "Option B pour question 5",
            "C": "Option C pour question 5",
            "D": "Option D pour question 5"
          },
          "correct_answer": "B",
          "explanation": "Explication pour l'exercice 5.",
          "difficulty_progression": 3
        },
        {
          "exercise_number": 6,
          "type": "vrai_faux",
          "passage_title": "Passage lecteur",
          "passage_text": "Attention: travaux.",
          "question": "Question 6 sur le passage?",
          "options": {},
          "correct_answer": "Vrai",
          "explanation": "Explication pour l'exercice 6.",
          "difficulty_progression": 1
        },
        {
          "exercise_number": 7,
          "type": "multiple_choice",
          "passage_title": "Passage lecteur",
          "passage_text": "Important: retards possibles.",
          "question": "Question 7 sur le passage?",
          "options": {
            "A": "Option A pour question 7",
            "B": "Option B pour question 7",
            "C": "Option C pour question 7",
            "D": "Option D pour question 7"
          },
          "correct_answer": "D",
          "explanation": "Explication pour l'exercice 7.",
          "difficulty_progression": 2
        },
        {
          "exercise_number": 8,
          "type": "vrai_faux",
          "passage_title": "Passage lecteur",
          "passage_text": "À bientôt.",
          "question": "Question 8 sur le passage?",
          "options": {},
          "correct_answer": "Vrai",
          "explanation": "Explication pour l'exercice 8.",
          "difficulty_progression": 3
        },
        {
          "exercise_number": 9,
          "type": "multiple_choice",
          "passage_title": "Passage lecteur",
          "passage_text": "Rappel: vaccination.",
          "question": "Question 9 sur le passage?",
          "options": {
            "A": "Option A pour question 9",
            "B": "Option B pour question 9",
            "C": "Option C pour question 9",
            "D": "Option D pour question 9"
          },
          "correct_answer": "B",
          "explanation": "Explication pour l'exercice 9.",
          "difficulty_progression": 1
        },
        {
          "exercise_number": 10,
          "type": "vrai_faux",
          "passage_title": "Passage lecteur",
          "passage_text": "Évitez aliments allergènes.",
          "question": "Question 10 sur le passage?",
          "options": {},
          "correct_answer": "Vrai",
          "explanation": "Explication pour l'exercice 10.",
          "difficulty_progression": 2
        }
      ]
    },
    {
      "lesson_number": 7,
      "title": "Courtes histoires",
      "slug": "a2-lecon-7-courtes-histoires",
      "objective": "Comprendre des textes de compréhension écrite niveau A2",
      "vocabulary_focus": [
        "jour",
        "matin",
        "soir",
        "nuit"
      ],
      "exercises": [
        {
          "exercise_number": 1,
          "type": "multiple_choice",
          "passage_title": "Passage lecteur",
          "passage_text": "Nous avons pique-niqué.",
          "question": "Question 1 sur le passage?",
          "options": {
            "A": "Option A pour question 1",
            "B": "Option B pour question 1",
            "C": "Option C pour question 1",
            "D": "Option D pour question 1"
          },
          "correct_answer": "B",
          "explanation": "Explication pour l'exercice 1.",
          "difficulty_progression": 2
        },
        {
          "exercise_number": 2,
          "type": "vrai_faux",
          "passage_title": "Passage lecteur",
          "passage_text": "Dimanche matin, il y a du soleil.",
          "question": "Question 2 sur le passage?",
          "options": {},
          "correct_answer": "Vrai",
          "explanation": "Explication pour l'exercice 2.",
          "difficulty_progression": 3
        },
        {
          "exercise_number": 3,
          "type": "multiple_choice",
          "passage_title": "Passage lecteur",
          "passage_text": "Allons à la plage!",
          "question": "Question 3 sur le passage?",
          "options": {
            "A": "Option A pour question 3",
            "B": "Option B pour question 3",
            "C": "Option C pour question 3",
            "D": "Option D pour question 3"
          },
          "correct_answer": "D",
          "explanation": "Explication pour l'exercice 3.",
          "difficulty_progression": 1
        },
        {
          "exercise_number": 4,
          "type": "vrai_faux",
          "passage_title": "Passage lecteur",
          "passage_text": "Le soir, on mange.",
          "question": "Question 4 sur le passage?",
          "options": {},
          "correct_answer": "Vrai",
          "explanation": "Explication pour l'exercice 4.",
          "difficulty_progression": 2
        },
        {
          "exercise_number": 5,
          "type": "multiple_choice",
          "passage_title": "Passage lecteur",
          "passage_text": "Hier, j'ai visité le parc.",
          "question": "Question 5 sur le passage?",
          "options": {
            "A": "Option A pour question 5",
            "B": "Option B pour question 5",
            "C": "Option C pour question 5",
            "D": "Option D pour question 5"
          },
          "correct_answer": "B",
          "explanation": "Explication pour l'exercice 5.",
          "difficulty_progression": 3
        },
        {
          "exercise_number": 6,
          "type": "vrai_faux",
          "passage_title": "Passage lecteur",
          "passage_text": "Nous avons pique-niqué.",
          "question": "Question 6 sur le passage?",
          "options": {},
          "correct_answer": "Vrai",
          "explanation": "Explication pour l'exercice 6.",
          "difficulty_progression": 1
        },
        {
          "exercise_number": 7,
          "type": "multiple_choice",
          "passage_title": "Passage lecteur",
          "passage_text": "Dimanche matin, il y a du soleil.",
          "question": "Question 7 sur le passage?",
          "options": {
            "A": "Option A pour question 7",
            "B": "Option B pour question 7",
            "C": "Option C pour question 7",
            "D": "Option D pour question 7"
          },
          "correct_answer": "D",
          "explanation": "Explication pour l'exercice 7.",
          "difficulty_progression": 2
        },
        {
          "exercise_number": 8,
          "type": "vrai_faux",
          "passage_title": "Passage lecteur",
          "passage_text": "Allons à la plage!",
          "question": "Question 8 sur le passage?",
          "options": {},
          "correct_answer": "Vrai",
          "explanation": "Explication pour l'exercice 8.",
          "difficulty_progression": 3
        },
        {
          "exercise_number": 9,
          "type": "multiple_choice",
          "passage_title": "Passage lecteur",
          "passage_text": "Le soir, on mange.",
          "question": "Question 9 sur le passage?",
          "options": {
            "A": "Option A pour question 9",
            "B": "Option B pour question 9",
            "C": "Option C pour question 9",
            "D": "Option D pour question 9"
          },
          "correct_answer": "B",
          "explanation": "Explication pour l'exercice 9.",
          "difficulty_progression": 1
        },
        {
          "exercise_number": 10,
          "type": "vrai_faux",
          "passage_title": "Passage lecteur",
          "passage_text": "Hier, j'ai visité le parc.",
          "question": "Question 10 sur le passage?",
          "options": {},
          "correct_answer": "Vrai",
          "explanation": "Explication pour l'exercice 10.",
          "difficulty_progression": 2
        }
      ]
    },
    {
      "lesson_number": 8,
      "title": "Itinéraires",
      "slug": "a2-lecon-8-itinéraires",
      "objective": "Comprendre des textes de compréhension écrite niveau A2",
      "vocabulary_focus": [
        "nord",
        "sud",
        "est",
        "ouest"
      ],
      "exercises": [
        {
          "exercise_number": 1,
          "type": "multiple_choice",
          "passage_title": "Passage lecteur",
          "passage_text": "École centre-ville.",
          "question": "Question 1 sur le passage?",
          "options": {
            "A": "Option A pour question 1",
            "B": "Option B pour question 1",
            "C": "Option C pour question 1",
            "D": "Option D pour question 1"
          },
          "correct_answer": "B",
          "explanation": "Explication pour l'exercice 1.",
          "difficulty_progression": 2
        },
        {
          "exercise_number": 2,
          "type": "vrai_faux",
          "passage_title": "Passage lecteur",
          "passage_text": "Parc à l'est.",
          "question": "Question 2 sur le passage?",
          "options": {},
          "correct_answer": "Vrai",
          "explanation": "Explication pour l'exercice 2.",
          "difficulty_progression": 3
        },
        {
          "exercise_number": 3,
          "type": "multiple_choice",
          "passage_title": "Passage lecteur",
          "passage_text": "Maison proche métro.",
          "question": "Question 3 sur le passage?",
          "options": {
            "A": "Option A pour question 3",
            "B": "Option B pour question 3",
            "C": "Option C pour question 3",
            "D": "Option D pour question 3"
          },
          "correct_answer": "D",
          "explanation": "Explication pour l'exercice 3.",
          "difficulty_progression": 1
        },
        {
          "exercise_number": 4,
          "type": "vrai_faux",
          "passage_title": "Passage lecteur",
          "passage_text": "Suivez la route.",
          "question": "Question 4 sur le passage?",
          "options": {},
          "correct_answer": "Vrai",
          "explanation": "Explication pour l'exercice 4.",
          "difficulty_progression": 2
        },
        {
          "exercise_number": 5,
          "type": "multiple_choice",
          "passage_title": "Passage lecteur",
          "passage_text": "Gare au nord.",
          "question": "Question 5 sur le passage?",
          "options": {
            "A": "Option A pour question 5",
            "B": "Option B pour question 5",
            "C": "Option C pour question 5",
            "D": "Option D pour question 5"
          },
          "correct_answer": "B",
          "explanation": "Explication pour l'exercice 5.",
          "difficulty_progression": 3
        },
        {
          "exercise_number": 6,
          "type": "vrai_faux",
          "passage_title": "Passage lecteur",
          "passage_text": "École centre-ville.",
          "question": "Question 6 sur le passage?",
          "options": {},
          "correct_answer": "Vrai",
          "explanation": "Explication pour l'exercice 6.",
          "difficulty_progression": 1
        },
        {
          "exercise_number": 7,
          "type": "multiple_choice",
          "passage_title": "Passage lecteur",
          "passage_text": "Parc à l'est.",
          "question": "Question 7 sur le passage?",
          "options": {
            "A": "Option A pour question 7",
            "B": "Option B pour question 7",
            "C": "Option C pour question 7",
            "D": "Option D pour question 7"
          },
          "correct_answer": "D",
          "explanation": "Explication pour l'exercice 7.",
          "difficulty_progression": 2
        },
        {
          "exercise_number": 8,
          "type": "vrai_faux",
          "passage_title": "Passage lecteur",
          "passage_text": "Maison proche métro.",
          "question": "Question 8 sur le passage?",
          "options": {},
          "correct_answer": "Vrai",
          "explanation": "Explication pour l'exercice 8.",
          "difficulty_progression": 3
        },
        {
          "exercise_number": 9,
          "type": "multiple_choice",
          "passage_title": "Passage lecteur",
          "passage_text": "Suivez la route.",
          "question": "Question 9 sur le passage?",
          "options": {
            "A": "Option A pour question 9",
            "B": "Option B pour question 9",
            "C": "Option C pour question 9",
            "D": "Option D pour question 9"
          },
          "correct_answer": "B",
          "explanation": "Explication pour l'exercice 9.",
          "difficulty_progression": 1
        },
        {
          "exercise_number": 10,
          "type": "vrai_faux",
          "passage_title": "Passage lecteur",
          "passage_text": "Gare au nord.",
          "question": "Question 10 sur le passage?",
          "options": {},
          "correct_answer": "Vrai",
          "explanation": "Explication pour l'exercice 10.",
          "difficulty_progression": 2
        }
      ]
    },
    {
      "lesson_number": 9,
      "title": "Menus et restauration",
      "slug": "a2-lecon-9-menus-et-restauration",
      "objective": "Comprendre des textes de compréhension écrite niveau A2",
      "vocabulary_focus": [
        "menu",
        "plat",
        "boisson"
      ],
      "exercises": [
        {
          "exercise_number": 1,
          "type": "multiple_choice",
          "passage_title": "Passage lecteur",
          "passage_text": "Boissons: eau, soda, vin.",
          "question": "Question 1 sur le passage?",
          "options": {
            "A": "Option A pour question 1",
            "B": "Option B pour question 1",
            "C": "Option C pour question 1",
            "D": "Option D pour question 1"
          },
          "correct_answer": "B",
          "explanation": "Explication pour l'exercice 1.",
          "difficulty_progression": 2
        },
        {
          "exercise_number": 2,
          "type": "vrai_faux",
          "passage_title": "Passage lecteur",
          "passage_text": "Dessert: glace.",
          "question": "Question 2 sur le passage?",
          "options": {},
          "correct_answer": "Vrai",
          "explanation": "Explication pour l'exercice 2.",
          "difficulty_progression": 3
        },
        {
          "exercise_number": 3,
          "type": "multiple_choice",
          "passage_title": "Passage lecteur",
          "passage_text": "Prix: menu 15€.",
          "question": "Question 3 sur le passage?",
          "options": {
            "A": "Option A pour question 3",
            "B": "Option B pour question 3",
            "C": "Option C pour question 3",
            "D": "Option D pour question 3"
          },
          "correct_answer": "D",
          "explanation": "Explication pour l'exercice 3.",
          "difficulty_progression": 1
        },
        {
          "exercise_number": 4,
          "type": "vrai_faux",
          "passage_title": "Passage lecteur",
          "passage_text": "Réservation obligatoire.",
          "question": "Question 4 sur le passage?",
          "options": {},
          "correct_answer": "Vrai",
          "explanation": "Explication pour l'exercice 4.",
          "difficulty_progression": 2
        },
        {
          "exercise_number": 5,
          "type": "multiple_choice",
          "passage_title": "Passage lecteur",
          "passage_text": "Aujourd'hui: soupe, poulet frites.",
          "question": "Question 5 sur le passage?",
          "options": {
            "A": "Option A pour question 5",
            "B": "Option B pour question 5",
            "C": "Option C pour question 5",
            "D": "Option D pour question 5"
          },
          "correct_answer": "B",
          "explanation": "Explication pour l'exercice 5.",
          "difficulty_progression": 3
        },
        {
          "exercise_number": 6,
          "type": "vrai_faux",
          "passage_title": "Passage lecteur",
          "passage_text": "Boissons: eau, soda, vin.",
          "question": "Question 6 sur le passage?",
          "options": {},
          "correct_answer": "Vrai",
          "explanation": "Explication pour l'exercice 6.",
          "difficulty_progression": 1
        },
        {
          "exercise_number": 7,
          "type": "multiple_choice",
          "passage_title": "Passage lecteur",
          "passage_text": "Dessert: glace.",
          "question": "Question 7 sur le passage?",
          "options": {
            "A": "Option A pour question 7",
            "B": "Option B pour question 7",
            "C": "Option C pour question 7",
            "D": "Option D pour question 7"
          },
          "correct_answer": "D",
          "explanation": "Explication pour l'exercice 7.",
          "difficulty_progression": 2
        },
        {
          "exercise_number": 8,
          "type": "vrai_faux",
          "passage_title": "Passage lecteur",
          "passage_text": "Prix: menu 15€.",
          "question": "Question 8 sur le passage?",
          "options": {},
          "correct_answer": "Vrai",
          "explanation": "Explication pour l'exercice 8.",
          "difficulty_progression": 3
        },
        {
          "exercise_number": 9,
          "type": "multiple_choice",
          "passage_title": "Passage lecteur",
          "passage_text": "Réservation obligatoire.",
          "question": "Question 9 sur le passage?",
          "options": {
            "A": "Option A pour question 9",
            "B": "Option B pour question 9",
            "C": "Option C pour question 9",
            "D": "Option D pour question 9"
          },
          "correct_answer": "B",
          "explanation": "Explication pour l'exercice 9.",
          "difficulty_progression": 1
        },
        {
          "exercise_number": 10,
          "type": "vrai_faux",
          "passage_title": "Passage lecteur",
          "passage_text": "Aujourd'hui: soupe, poulet frites.",
          "question": "Question 10 sur le passage?",
          "options": {},
          "correct_answer": "Vrai",
          "explanation": "Explication pour l'exercice 10.",
          "difficulty_progression": 2
        }
      ]
    },
    {
      "lesson_number": 10,
      "title": "Billets et tickets",
      "slug": "a2-lecon-10-billets-et-tickets",
      "objective": "Comprendre des textes de compréhension écrite niveau A2",
      "vocabulary_focus": [
        "validité",
        "tarif",
        "classe"
      ],
      "exercises": [
        {
          "exercise_number": 1,
          "type": "multiple_choice",
          "passage_title": "Passage lecteur",
          "passage_text": "Départ 10h00.",
          "question": "Question 1 sur le passage?",
          "options": {
            "A": "Option A pour question 1",
            "B": "Option B pour question 1",
            "C": "Option C pour question 1",
            "D": "Option D pour question 1"
          },
          "correct_answer": "B",
          "explanation": "Explication pour l'exercice 1.",
          "difficulty_progression": 2
        },
        {
          "exercise_number": 2,
          "type": "vrai_faux",
          "passage_title": "Passage lecteur",
          "passage_text": "Arrivée 12h30.",
          "question": "Question 2 sur le passage?",
          "options": {},
          "correct_answer": "Vrai",
          "explanation": "Explication pour l'exercice 2.",
          "difficulty_progression": 3
        },
        {
          "exercise_number": 3,
          "type": "multiple_choice",
          "passage_title": "Passage lecteur",
          "passage_text": "Place 12, voiture 3.",
          "question": "Question 3 sur le passage?",
          "options": {
            "A": "Option A pour question 3",
            "B": "Option B pour question 3",
            "C": "Option C pour question 3",
            "D": "Option D pour question 3"
          },
          "correct_answer": "D",
          "explanation": "Explication pour l'exercice 3.",
          "difficulty_progression": 1
        },
        {
          "exercise_number": 4,
          "type": "vrai_faux",
          "passage_title": "Passage lecteur",
          "passage_text": "Valable 48h.",
          "question": "Question 4 sur le passage?",
          "options": {},
          "correct_answer": "Vrai",
          "explanation": "Explication pour l'exercice 4.",
          "difficulty_progression": 2
        },
        {
          "exercise_number": 5,
          "type": "multiple_choice",
          "passage_title": "Passage lecteur",
          "passage_text": "Billet train Paris-Lyon.",
          "question": "Question 5 sur le passage?",
          "options": {
            "A": "Option A pour question 5",
            "B": "Option B pour question 5",
            "C": "Option C pour question 5",
            "D": "Option D pour question 5"
          },
          "correct_answer": "B",
          "explanation": "Explication pour l'exercice 5.",
          "difficulty_progression": 3
        },
        {
          "exercise_number": 6,
          "type": "vrai_faux",
          "passage_title": "Passage lecteur",
          "passage_text": "Départ 10h00.",
          "question": "Question 6 sur le passage?",
          "options": {},
          "correct_answer": "Vrai",
          "explanation": "Explication pour l'exercice 6.",
          "difficulty_progression": 1
        },
        {
          "exercise_number": 7,
          "type": "multiple_choice",
          "passage_title": "Passage lecteur",
          "passage_text": "Arrivée 12h30.",
          "question": "Question 7 sur le passage?",
          "options": {
            "A": "Option A pour question 7",
            "B": "Option B pour question 7",
            "C": "Option C pour question 7",
            "D": "Option D pour question 7"
          },
          "correct_answer": "D",
          "explanation": "Explication pour l'exercice 7.",
          "difficulty_progression": 2
        },
        {
          "exercise_number": 8,
          "type": "vrai_faux",
          "passage_title": "Passage lecteur",
          "passage_text": "Place 12, voiture 3.",
          "question": "Question 8 sur le passage?",
          "options": {},
          "correct_answer": "Vrai",
          "explanation": "Explication pour l'exercice 8.",
          "difficulty_progression": 3
        },
        {
          "exercise_number": 9,
          "type": "multiple_choice",
          "passage_title": "Passage lecteur",
          "passage_text": "Valable 48h.",
          "question": "Question 9 sur le passage?",
          "options": {
            "A": "Option A pour question 9",
            "B": "Option B pour question 9",
            "C": "Option C pour question 9",
            "D": "Option D pour question 9"
          },
          "correct_answer": "B",
          "explanation": "Explication pour l'exercice 9.",
          "difficulty_progression": 1
        },
        {
          "exercise_number": 10,
          "type": "vrai_faux",
          "passage_title": "Passage lecteur",
          "passage_text": "Billet train Paris-Lyon.",
          "question": "Question 10 sur le passage?",
          "options": {},
          "correct_answer": "Vrai",
          "explanation": "Explication pour l'exercice 10.",
          "difficulty_progression": 2
        }
      ]
    },
    {
      "lesson_number": 11,
      "title": "Avis et notes",
      "slug": "a2-lecon-11-avis-et-notes",
      "objective": "Comprendre des textes de compréhension écrite niveau A2",
      "vocabulary_focus": [
        "avis",
        "fermeture",
        "réouverture"
      ],
      "exercises": [
        {
          "exercise_number": 1,
          "type": "multiple_choice",
          "passage_title": "Passage lecteur",
          "passage_text": "Réouverture jeudi.",
          "question": "Question 1 sur le passage?",
          "options": {
            "A": "Option A pour question 1",
            "B": "Option B pour question 1",
            "C": "Option C pour question 1",
            "D": "Option D pour question 1"
          },
          "correct_answer": "B",
          "explanation": "Explication pour l'exercice 1.",
          "difficulty_progression": 2
        },
        {
          "exercise_number": 2,
          "type": "vrai_faux",
          "passage_title": "Passage lecteur",
          "passage_text": "Travaux en cours.",
          "question": "Question 2 sur le passage?",
          "options": {},
          "correct_answer": "Vrai",
          "explanation": "Explication pour l'exercice 2.",
          "difficulty_progression": 3
        },
        {
          "exercise_number": 3,
          "type": "multiple_choice",
          "passage_title": "Passage lecteur",
          "passage_text": "Merci pour votre patience.",
          "question": "Question 3 sur le passage?",
          "options": {
            "A": "Option A pour question 3",
            "B": "Option B pour question 3",
            "C": "Option C pour question 3",
            "D": "Option D pour question 3"
          },
          "correct_answer": "D",
          "explanation": "Explication pour l'exercice 3.",
          "difficulty_progression": 1
        },
        {
          "exercise_number": 4,
          "type": "vrai_faux",
          "passage_title": "Passage lecteur",
          "passage_text": "À bientôt!",
          "question": "Question 4 sur le passage?",
          "options": {},
          "correct_answer": "Vrai",
          "explanation": "Explication pour l'exercice 4.",
          "difficulty_progression": 2
        },
        {
          "exercise_number": 5,
          "type": "multiple_choice",
          "passage_title": "Passage lecteur",
          "passage_text": "Fermeture exceptionnelle demain.",
          "question": "Question 5 sur le passage?",
          "options": {
            "A": "Option A pour question 5",
            "B": "Option B pour question 5",
            "C": "Option C pour question 5",
            "D": "Option D pour question 5"
          },
          "correct_answer": "B",
          "explanation": "Explication pour l'exercice 5.",
          "difficulty_progression": 3
        },
        {
          "exercise_number": 6,
          "type": "vrai_faux",
          "passage_title": "Passage lecteur",
          "passage_text": "Réouverture jeudi.",
          "question": "Question 6 sur le passage?",
          "options": {},
          "correct_answer": "Vrai",
          "explanation": "Explication pour l'exercice 6.",
          "difficulty_progression": 1
        },
        {
          "exercise_number": 7,
          "type": "multiple_choice",
          "passage_title": "Passage lecteur",
          "passage_text": "Travaux en cours.",
          "question": "Question 7 sur le passage?",
          "options": {
            "A": "Option A pour question 7",
            "B": "Option B pour question 7",
            "C": "Option C pour question 7",
            "D": "Option D pour question 7"
          },
          "correct_answer": "D",
          "explanation": "Explication pour l'exercice 7.",
          "difficulty_progression": 2
        },
        {
          "exercise_number": 8,
          "type": "vrai_faux",
          "passage_title": "Passage lecteur",
          "passage_text": "Merci pour votre patience.",
          "question": "Question 8 sur le passage?",
          "options": {},
          "correct_answer": "Vrai",
          "explanation": "Explication pour l'exercice 8.",
          "difficulty_progression": 3
        },
        {
          "exercise_number": 9,
          "type": "multiple_choice",
          "passage_title": "Passage lecteur",
          "passage_text": "À bientôt!",
          "question": "Question 9 sur le passage?",
          "options": {
            "A": "Option A pour question 9",
            "B": "Option B pour question 9",
            "C": "Option C pour question 9",
            "D": "Option D pour question 9"
          },
          "correct_answer": "B",
          "explanation": "Explication pour l'exercice 9.",
          "difficulty_progression": 1
        },
        {
          "exercise_number": 10,
          "type": "vrai_faux",
          "passage_title": "Passage lecteur",
          "passage_text": "Fermeture exceptionnelle demain.",
          "question": "Question 10 sur le passage?",
          "options": {},
          "correct_answer": "Vrai",
          "explanation": "Explication pour l'exercice 10.",
          "difficulty_progression": 2
        }
      ]
    },
    {
      "lesson_number": 12,
      "title": "Échange de messages",
      "slug": "a2-lecon-12-échange-de-messages",
      "objective": "Comprendre des textes de compréhension écrite niveau A2",
      "vocabulary_focus": [
        "réponds",
        "question",
        "réponse"
      ],
      "exercises": [
        {
          "exercise_number": 1,
          "type": "multiple_choice",
          "passage_title": "Passage lecteur",
          "passage_text": "Ça va bien, et toi?",
          "question": "Question 1 sur le passage?",
          "options": {
            "A": "Option A pour question 1",
            "B": "Option B pour question 1",
            "C": "Option C pour question 1",
            "D": "Option D pour question 1"
          },
          "correct_answer": "B",
          "explanation": "Explication pour l'exercice 1.",
          "difficulty_progression": 2
        },
        {
          "exercise_number": 2,
          "type": "vrai_faux",
          "passage_title": "Passage lecteur",
          "passage_text": "Tu viens samedi?",
          "question": "Question 2 sur le passage?",
          "options": {},
          "correct_answer": "Vrai",
          "explanation": "Explication pour l'exercice 2.",
          "difficulty_progression": 3
        },
        {
          "exercise_number": 3,
          "type": "multiple_choice",
          "passage_title": "Passage lecteur",
          "passage_text": "Oui, à 20h.",
          "question": "Question 3 sur le passage?",
          "options": {
            "A": "Option A pour question 3",
            "B": "Option B pour question 3",
            "C": "Option C pour question 3",
            "D": "Option D pour question 3"
          },
          "correct_answer": "D",
          "explanation": "Explication pour l'exercice 3.",
          "difficulty_progression": 1
        },
        {
          "exercise_number": 4,
          "type": "vrai_faux",
          "passage_title": "Passage lecteur",
          "passage_text": "À plus tard!",
          "question": "Question 4 sur le passage?",
          "options": {},
          "correct_answer": "Vrai",
          "explanation": "Explication pour l'exercice 4.",
          "difficulty_progression": 2
        },
        {
          "exercise_number": 5,
          "type": "multiple_choice",
          "passage_title": "Passage lecteur",
          "passage_text": "Comment ça va?",
          "question": "Question 5 sur le passage?",
          "options": {
            "A": "Option A pour question 5",
            "B": "Option B pour question 5",
            "C": "Option C pour question 5",
            "D": "Option D pour question 5"
          },
          "correct_answer": "B",
          "explanation": "Explication pour l'exercice 5.",
          "difficulty_progression": 3
        },
        {
          "exercise_number": 6,
          "type": "vrai_faux",
          "passage_title": "Passage lecteur",
          "passage_text": "Ça va bien, et toi?",
          "question": "Question 6 sur le passage?",
          "options": {},
          "correct_answer": "Vrai",
          "explanation": "Explication pour l'exercice 6.",
          "difficulty_progression": 1
        },
        {
          "exercise_number": 7,
          "type": "multiple_choice",
          "passage_title": "Passage lecteur",
          "passage_text": "Tu viens samedi?",
          "question": "Question 7 sur le passage?",
          "options": {
            "A": "Option A pour question 7",
            "B": "Option B pour question 7",
            "C": "Option C pour question 7",
            "D": "Option D pour question 7"
          },
          "correct_answer": "D",
          "explanation": "Explication pour l'exercice 7.",
          "difficulty_progression": 2
        },
        {
          "exercise_number": 8,
          "type": "vrai_faux",
          "passage_title": "Passage lecteur",
          "passage_text": "Oui, à 20h.",
          "question": "Question 8 sur le passage?",
          "options": {},
          "correct_answer": "Vrai",
          "explanation": "Explication pour l'exercice 8.",
          "difficulty_progression": 3
        },
        {
          "exercise_number": 9,
          "type": "multiple_choice",
          "passage_title": "Passage lecteur",
          "passage_text": "À plus tard!",
          "question": "Question 9 sur le passage?",
          "options": {
            "A": "Option A pour question 9",
            "B": "Option B pour question 9",
            "C": "Option C pour question 9",
            "D": "Option D pour question 9"
          },
          "correct_answer": "B",
          "explanation": "Explication pour l'exercice 9.",
          "difficulty_progression": 1
        },
        {
          "exercise_number": 10,
          "type": "vrai_faux",
          "passage_title": "Passage lecteur",
          "passage_text": "Comment ça va?",
          "question": "Question 10 sur le passage?",
          "options": {},
          "correct_answer": "Vrai",
          "explanation": "Explication pour l'exercice 10.",
          "difficulty_progression": 2
        }
      ]
    },
    {
      "lesson_number": 13,
      "title": "Informations pratiques",
      "slug": "a2-lecon-13-informations-pratiques",
      "objective": "Comprendre des textes de compréhension écrite niveau A2",
      "vocabulary_focus": [
        "info",
        "numéro",
        "adresse"
      ],
      "exercises": [
        {
          "exercise_number": 1,
          "type": "multiple_choice",
          "passage_title": "Passage lecteur",
          "passage_text": "Adresse: 10 rue du Centre.",
          "question": "Question 1 sur le passage?",
          "options": {
            "A": "Option A pour question 1",
            "B": "Option B pour question 1",
            "C": "Option C pour question 1",
            "D": "Option D pour question 1"
          },
          "correct_answer": "B",
          "explanation": "Explication pour l'exercice 1.",
          "difficulty_progression": 2
        },
        {
          "exercise_number": 2,
          "type": "vrai_faux",
          "passage_title": "Passage lecteur",
          "passage_text": "Email: info@example.com.",
          "question": "Question 2 sur le passage?",
          "options": {},
          "correct_answer": "Vrai",
          "explanation": "Explication pour l'exercice 2.",
          "difficulty_progression": 3
        },
        {
          "exercise_number": 3,
          "type": "multiple_choice",
          "passage_title": "Passage lecteur",
          "passage_text": "Site: www.example.fr.",
          "question": "Question 3 sur le passage?",
          "options": {
            "A": "Option A pour question 3",
            "B": "Option B pour question 3",
            "C": "Option C pour question 3",
            "D": "Option D pour question 3"
          },
          "correct_answer": "D",
          "explanation": "Explication pour l'exercice 3.",
          "difficulty_progression": 1
        },
        {
          "exercise_number": 4,
          "type": "vrai_faux",
          "passage_title": "Passage lecteur",
          "passage_text": "Horaires sur demande.",
          "question": "Question 4 sur le passage?",
          "options": {},
          "correct_answer": "Vrai",
          "explanation": "Explication pour l'exercice 4.",
          "difficulty_progression": 2
        },
        {
          "exercise_number": 5,
          "type": "multiple_choice",
          "passage_title": "Passage lecteur",
          "passage_text": "Tél: 01 23 45 67 89.",
          "question": "Question 5 sur le passage?",
          "options": {
            "A": "Option A pour question 5",
            "B": "Option B pour question 5",
            "C": "Option C pour question 5",
            "D": "Option D pour question 5"
          },
          "correct_answer": "B",
          "explanation": "Explication pour l'exercice 5.",
          "difficulty_progression": 3
        },
        {
          "exercise_number": 6,
          "type": "vrai_faux",
          "passage_title": "Passage lecteur",
          "passage_text": "Adresse: 10 rue du Centre.",
          "question": "Question 6 sur le passage?",
          "options": {},
          "correct_answer": "Vrai",
          "explanation": "Explication pour l'exercice 6.",
          "difficulty_progression": 1
        },
        {
          "exercise_number": 7,
          "type": "multiple_choice",
          "passage_title": "Passage lecteur",
          "passage_text": "Email: info@example.com.",
          "question": "Question 7 sur le passage?",
          "options": {
            "A": "Option A pour question 7",
            "B": "Option B pour question 7",
            "C": "Option C pour question 7",
            "D": "Option D pour question 7"
          },
          "correct_answer": "D",
          "explanation": "Explication pour l'exercice 7.",
          "difficulty_progression": 2
        },
        {
          "exercise_number": 8,
          "type": "vrai_faux",
          "passage_title": "Passage lecteur",
          "passage_text": "Site: www.example.fr.",
          "question": "Question 8 sur le passage?",
          "options": {},
          "correct_answer": "Vrai",
          "explanation": "Explication pour l'exercice 8.",
          "difficulty_progression": 3
        },
        {
          "exercise_number": 9,
          "type": "multiple_choice",
          "passage_title": "Passage lecteur",
          "passage_text": "Horaires sur demande.",
          "question": "Question 9 sur le passage?",
          "options": {
            "A": "Option A pour question 9",
            "B": "Option B pour question 9",
            "C": "Option C pour question 9",
            "D": "Option D pour question 9"
          },
          "correct_answer": "B",
          "explanation": "Explication pour l'exercice 9.",
          "difficulty_progression": 1
        },
        {
          "exercise_number": 10,
          "type": "vrai_faux",
          "passage_title": "Passage lecteur",
          "passage_text": "Tél: 01 23 45 67 89.",
          "question": "Question 10 sur le passage?",
          "options": {},
          "correct_answer": "Vrai",
          "explanation": "Explication pour l'exercice 10.",
          "difficulty_progression": 2
        }
      ]
    },
    {
      "lesson_number": 14,
      "title": "Publicités simples",
      "slug": "a2-lecon-14-publicités-simples",
      "objective": "Comprendre des textes de compréhension écrite niveau A2",
      "vocabulary_focus": [
        "offre",
        "solde",
        "promo"
      ],
      "exercises": [
        {
          "exercise_number": 1,
          "type": "multiple_choice",
          "passage_title": "Passage lecteur",
          "passage_text": "2 pour 10 euros.",
          "question": "Question 1 sur le passage?",
          "options": {
            "A": "Option A pour question 1",
            "B": "Option B pour question 1",
            "C": "Option C pour question 1",
            "D": "Option D pour question 1"
          },
          "correct_answer": "B",
          "explanation": "Explication pour l'exercice 1.",
          "difficulty_progression": 2
        },
        {
          "exercise_number": 2,
          "type": "vrai_faux",
          "passage_title": "Passage lecteur",
          "passage_text": "Gratuit ce week-end.",
          "question": "Question 2 sur le passage?",
          "options": {},
          "correct_answer": "Vrai",
          "explanation": "Explication pour l'exercice 2.",
          "difficulty_progression": 3
        },
        {
          "exercise_number": 3,
          "type": "multiple_choice",
          "passage_title": "Passage lecteur",
          "passage_text": "Livraison offerte.",
          "question": "Question 3 sur le passage?",
          "options": {
            "A": "Option A pour question 3",
            "B": "Option B pour question 3",
            "C": "Option C pour question 3",
            "D": "Option D pour question 3"
          },
          "correct_answer": "D",
          "explanation": "Explication pour l'exercice 3.",
          "difficulty_progression": 1
        },
        {
          "exercise_number": 4,
          "type": "vrai_faux",
          "passage_title": "Passage lecteur",
          "passage_text": "Stock limité!",
          "question": "Question 4 sur le passage?",
          "options": {},
          "correct_answer": "Vrai",
          "explanation": "Explication pour l'exercice 4.",
          "difficulty_progression": 2
        },
        {
          "exercise_number": 5,
          "type": "multiple_choice",
          "passage_title": "Passage lecteur",
          "passage_text": "Grand solde jusqu'à 70%!",
          "question": "Question 5 sur le passage?",
          "options": {
            "A": "Option A pour question 5",
            "B": "Option B pour question 5",
            "C": "Option C pour question 5",
            "D": "Option D pour question 5"
          },
          "correct_answer": "B",
          "explanation": "Explication pour l'exercice 5.",
          "difficulty_progression": 3
        },
        {
          "exercise_number": 6,
          "type": "vrai_faux",
          "passage_title": "Passage lecteur",
          "passage_text": "2 pour 10 euros.",
          "question": "Question 6 sur le passage?",
          "options": {},
          "correct_answer": "Vrai",
          "explanation": "Explication pour l'exercice 6.",
          "difficulty_progression": 1
        },
        {
          "exercise_number": 7,
          "type": "multiple_choice",
          "passage_title": "Passage lecteur",
          "passage_text": "Gratuit ce week-end.",
          "question": "Question 7 sur le passage?",
          "options": {
            "A": "Option A pour question 7",
            "B": "Option B pour question 7",
            "C": "Option C pour question 7",
            "D": "Option D pour question 7"
          },
          "correct_answer": "D",
          "explanation": "Explication pour l'exercice 7.",
          "difficulty_progression": 2
        },
        {
          "exercise_number": 8,
          "type": "vrai_faux",
          "passage_title": "Passage lecteur",
          "passage_text": "Livraison offerte.",
          "question": "Question 8 sur le passage?",
          "options": {},
          "correct_answer": "Vrai",
          "explanation": "Explication pour l'exercice 8.",
          "difficulty_progression": 3
        },
        {
          "exercise_number": 9,
          "type": "multiple_choice",
          "passage_title": "Passage lecteur",
          "passage_text": "Stock limité!",
          "question": "Question 9 sur le passage?",
          "options": {
            "A": "Option A pour question 9",
            "B": "Option B pour question 9",
            "C": "Option C pour question 9",
            "D": "Option D pour question 9"
          },
          "correct_answer": "B",
          "explanation": "Explication pour l'exercice 9.",
          "difficulty_progression": 1
        },
        {
          "exercise_number": 10,
          "type": "vrai_faux",
          "passage_title": "Passage lecteur",
          "passage_text": "Grand solde jusqu'à 70%!",
          "question": "Question 10 sur le passage?",
          "options": {},
          "correct_answer": "Vrai",
          "explanation": "Explication pour l'exercice 10.",
          "difficulty_progression": 2
        }
      ]
    },
    {
      "lesson_number": 15,
      "title": "Conseils de santé",
      "slug": "a2-lecon-15-conseils-de-santé",
      "objective": "Comprendre des textes de compréhension écrite niveau A2",
      "vocabulary_focus": [
        "sommeil",
        "alimentation",
        "sport"
      ],
      "exercises": [
        {
          "exercise_number": 1,
          "type": "multiple_choice",
          "passage_title": "Passage lecteur",
          "passage_text": "Mangez fruits et légumes.",
          "question": "Question 1 sur le passage?",
          "options": {
            "A": "Option A pour question 1",
            "B": "Option B pour question 1",
            "C": "Option C pour question 1",
            "D": "Option D pour question 1"
          },
          "correct_answer": "B",
          "explanation": "Explication pour l'exercice 1.",
          "difficulty_progression": 2
        },
        {
          "exercise_number": 2,
          "type": "vrai_faux",
          "passage_title": "Passage lecteur",
          "passage_text": "Faites du sport.",
          "question": "Question 2 sur le passage?",
          "options": {},
          "correct_answer": "Vrai",
          "explanation": "Explication pour l'exercice 2.",
          "difficulty_progression": 3
        },
        {
          "exercise_number": 3,
          "type": "multiple_choice",
          "passage_title": "Passage lecteur",
          "passage_text": "Buvez 2 litres eau.",
          "question": "Question 3 sur le passage?",
          "options": {
            "A": "Option A pour question 3",
            "B": "Option B pour question 3",
            "C": "Option C pour question 3",
            "D": "Option D pour question 3"
          },
          "correct_answer": "D",
          "explanation": "Explication pour l'exercice 3.",
          "difficulty_progression": 1
        },
        {
          "exercise_number": 4,
          "type": "vrai_faux",
          "passage_title": "Passage lecteur",
          "passage_text": "Reposez-vous!",
          "question": "Question 4 sur le passage?",
          "options": {},
          "correct_answer": "Vrai",
          "explanation": "Explication pour l'exercice 4.",
          "difficulty_progression": 2
        },
        {
          "exercise_number": 5,
          "type": "multiple_choice",
          "passage_title": "Passage lecteur",
          "passage_text": "Dormez 8 heures.",
          "question": "Question 5 sur le passage?",
          "options": {
            "A": "Option A pour question 5",
            "B": "Option B pour question 5",
            "C": "Option C pour question 5",
            "D": "Option D pour question 5"
          },
          "correct_answer": "B",
          "explanation": "Explication pour l'exercice 5.",
          "difficulty_progression": 3
        },
        {
          "exercise_number": 6,
          "type": "vrai_faux",
          "passage_title": "Passage lecteur",
          "passage_text": "Mangez fruits et légumes.",
          "question": "Question 6 sur le passage?",
          "options": {},
          "correct_answer": "Vrai",
          "explanation": "Explication pour l'exercice 6.",
          "difficulty_progression": 1
        },
        {
          "exercise_number": 7,
          "type": "multiple_choice",
          "passage_title": "Passage lecteur",
          "passage_text": "Faites du sport.",
          "question": "Question 7 sur le passage?",
          "options": {
            "A": "Option A pour question 7",
            "B": "Option B pour question 7",
            "C": "Option C pour question 7",
            "D": "Option D pour question 7"
          },
          "correct_answer": "D",
          "explanation": "Explication pour l'exercice 7.",
          "difficulty_progression": 2
        },
        {
          "exercise_number": 8,
          "type": "vrai_faux",
          "passage_title": "Passage lecteur",
          "passage_text": "Buvez 2 litres eau.",
          "question": "Question 8 sur le passage?",
          "options": {},
          "correct_answer": "Vrai",
          "explanation": "Explication pour l'exercice 8.",
          "difficulty_progression": 3
        },
        {
          "exercise_number": 9,
          "type": "multiple_choice",
          "passage_title": "Passage lecteur",
          "passage_text": "Reposez-vous!",
          "question": "Question 9 sur le passage?",
          "options": {
            "A": "Option A pour question 9",
            "B": "Option B pour question 9",
            "C": "Option C pour question 9",
            "D": "Option D pour question 9"
          },
          "correct_answer": "B",
          "explanation": "Explication pour l'exercice 9.",
          "difficulty_progression": 1
        },
        {
          "exercise_number": 10,
          "type": "vrai_faux",
          "passage_title": "Passage lecteur",
          "passage_text": "Dormez 8 heures.",
          "question": "Question 10 sur le passage?",
          "options": {},
          "correct_answer": "Vrai",
          "explanation": "Explication pour l'exercice 10.",
          "difficulty_progression": 2
        }
      ]
    }
  ]
}